{
  "$schema": "https://developer.microsoft.com/json-schemas/fabric/item/report/definition/visualContainer/1.6.0/schema.json",
  "name": "05800a0989c2219c6f7b",
  "position": {
    "x": 647.91666666666674,
    "y": 93.75,
    "z": 4000,
    "height": 101.04166666666667,
    "width": 194.79166666666669,
    "tabOrder": 4000
  },
  "visual": {
    "visualType": "card",
    "query": {
      "queryState": {
        "Values": {
          "projections": [
            {
              "field": {
                "Measure": {
                  "Expression": {
                    "SourceRef": {
                      "Entity": "Measure group"
                    }
                  },
                  "Property": "Total profits"
                }
              },
              "queryRef": "Orders.Total profits",
              "nativeQueryRef": "Total profits"
            }
          ]
        }
      },
      "sortDefinition": {
        "sort": [
          {
            "field": {
              "Measure": {
                "Expression": {
                  "SourceRef": {
                    "Entity": "Measure group"
                  }
                },
                "Property": "Total profits"
              }
            },
            "direction": "Descending"
          }
        ],
        "isDefaultSort": true
      }
    },
    "objects": {
      "labels": [
        {
          "properties": {
            "fontSize": {
              "expr": {
                "Literal": {
                  "Value": "30D"
                }
              }
            },
            "color": {
              "solid": {
                "color": {
                  "expr": {
                    "ThemeDataColor": {
                      "ColorId": 0,
                      "Percent": 0
                    }
                  }
                }
              }
            }
          }
        }
      ],
      "categoryLabels": [
        {
          "properties": {
            "color": {
              "solid": {
                "color": {
                  "expr": {
                    "ThemeDataColor": {
                      "ColorId": 0,
                      "Percent": 0
                    }
                  }
                }
              }
            }
          }
        }
      ]
    },
    "visualContainerObjects": {
      "background": [
        {
          "properties": {
            "color": {
              "solid": {
                "color": {
                  "expr": {
                    "Literal": {
                      "Value": "'#3A3A3A'"
                    }
                  }
                }
              }
            }
          }
        }
      ]
    },
    "drillFilterOtherVisuals": true
  }
}